ceylonai_next-0.3.6.dist-info/METADATA
ceylonai_next-0.3.6.dist-info/WHEEL
ceylonai_next-0.3.6.dist-info/licenses/LICENSE
ceylonai_next/__init__.py
ceylonai_next/__init__.pyi
ceylonai_next/_utils/__init__.py
ceylonai_next/_utils/schema.py
ceylonai_next/agent/__init__.py
ceylonai_next/agent/base.py
ceylonai_next/agent/llm.py
ceylonai_next/ceylonai_next.abi3.so
ceylonai_next/logging/__init__.py
ceylonai_next/logging/config.py
ceylonai_next/memory/__init__.py
ceylonai_next/memory/backends.py
ceylonai_next/mesh/__init__.py
ceylonai_next/mesh/async_processor.py
ceylonai_next/mesh/distributed.py
ceylonai_next/mesh/local.py
ceylonai_next/py.typed
ceylonai_next/react/__init__.py
ceylonai_next/react/core.py
ceylonai_next/types/__init__.py
ceylonai_next/types/mesh_types.py
ceylonai_next-0.3.6.dist-info/RECORD
