Metadata-Version: 2.4
Name: ceylonai-next
Version: 0.3.6
Classifier: Development Status :: 3 - Alpha
Classifier: Intended Audience :: Developers
Classifier: Topic :: Software Development :: Libraries :: Python Modules
Classifier: Topic :: Scientific/Engineering :: Artificial Intelligence
Classifier: License :: OSI Approved :: MIT License
Classifier: Programming Language :: Python :: 3
Classifier: Programming Language :: Python :: 3.9
Classifier: Programming Language :: Python :: 3.10
Classifier: Programming Language :: Python :: 3.11
Classifier: Programming Language :: Python :: 3.12
Classifier: Programming Language :: Rust
Classifier: Programming Language :: Python :: Implementation :: CPython
Classifier: Programming Language :: Python :: Implementation :: PyPy
Requires-Dist: pytest>=7.0.0 ; extra == 'dev'
Requires-Dist: pytest-asyncio>=0.21.0 ; extra == 'dev'
Provides-Extra: dev
License-File: LICENSE
Summary: Ceylon: A Rust-based agent mesh framework for building local and distributed AI agent systems
Keywords: ai,agents,llm,mesh,distributed,async,rust,ollama
Author-email: Ceylon AI <contact@ceylon.ai>
Requires-Python: >=3.9
Project-URL: Homepage, https://github.com/ceylonai/ceylon
Project-URL: Repository, https://github.com/ceylonai/ceylon
Project-URL: Documentation, https://github.com/ceylonai/ceylon/tree/main/docs
Project-URL: Issues, https://github.com/ceylonai/ceylon/issues
